treestruct/__init__.py
treestruct/helpers.py
treestruct/visualize.py
treestruct-0.1.5.dist-info/LICENSE
treestruct-0.1.5.dist-info/WHEEL
treestruct-0.1.5.dist-info/METADATA
treestruct-0.1.5.dist-info/RECORD
