Metadata-Version: 2.1
Name: treestruct
Version: 0.1.5
Summary: Simplify the task of creating, traversing, manipulating and visualizing tree structures
Home-page: UNKNOWN
License: MIT
Author: Shady Rafehi
Author-email: shadyrafehi@gmail.com
Requires-Python: >=2.7, !=3.0.*, !=3.1.*, !=3.2.*, !=3.3.*, !=3.4.*
Classifier: License :: OSI Approved :: MIT License
Classifier: Programming Language :: Python :: 2
Classifier: Programming Language :: Python :: 2.7
Classifier: Programming Language :: Python :: 3
Classifier: Programming Language :: Python :: 3.5
Classifier: Programming Language :: Python :: 3.6
Classifier: Programming Language :: Python :: 3.7
Requires-Dist: graphviz (>=0.13.0,<0.14.0)
